LICENSE
pymongo_the_sql/__init__.py
pymongo_the_sql/pymongo_the_sql.py
pymongo_the_sql/simple_py_sql.py
pymongo_the_sql-0.0.4.dist-info/LICENSE
pymongo_the_sql-0.0.4.dist-info/WHEEL
pymongo_the_sql-0.0.4.dist-info/METADATA
pymongo_the_sql-0.0.4.dist-info/RECORD
