Metadata-Version: 2.1
Name: pymongo-the-sql
Version: 0.0.4
Summary: A sql wrapper made to mimic the pymongo syntax in order to simplify sql syntax.
Home-page: https://appsight.se
License: MIT
Author: Marcus Bader
Author-email: marcus@appsight.se
Requires-Python: >=3.6,<4.0
Classifier: License :: OSI Approved :: MIT License
Classifier: Programming Language :: Python :: 3
Classifier: Programming Language :: Python :: 3.6
Classifier: Programming Language :: Python :: 3.7
Classifier: Programming Language :: Python :: 3.8
Classifier: Programming Language :: Python :: 3.9
Project-URL: Repository, https://github.com/marbad1994/pymongo-the-sql
